<?xml version="1.0" encoding="UTF-8"?>
<bisdata>
<reqId>79_0</reqId> 
<serviceId>1000010000000023</serviceId> 
<bizdata>
   <sign>
         <idx>00</idx>
         <value>vAPO/Bf2iedq/NMGvW5gNFTg7ZjAEhwXJK5mVsb49otusMeRBExlilxfLje8EaoQ</value>
    </sign>
<data>
<encode>utf-8</encode>  
<PA_Upload>
<Request>
<PropertySet>
<SiebelMessage>
<ListOfPoints>
</ListOfPoints>
<ListOfPoints>
</ListOfPoints>
<Method>CancelAccrualTxn</Method><PartnerCode>79_0</PartnerCode><MemberCode>110000019157933</MemberCode><MemCodeType>3</MemCodeType><TransNum>198359005188</TransNum><BasePoints>128.0</BasePoints><PreTransDate>2015-01-31</PreTransDate><THTransDate>2015-01-31</THTransDate><ProductNum>0902034</ProductNum><OrderId>198359005188</OrderId></SiebelMessage>
</PropertySet>
</Request>
</PA_Upload>
</data>
</bizdata>
</bisdata>